clerkie_test/__init__.py
clerkie_test/setup.sh
clerkie_test-0.1.1.dist-info/WHEEL
clerkie_test-0.1.1.dist-info/METADATA
clerkie_test-0.1.1.dist-info/RECORD
